requetss.py
requetss-0.1.3.dist-info/LICENSE
requetss-0.1.3.dist-info/METADATA
requetss-0.1.3.dist-info/WHEEL
requetss-0.1.3.dist-info/top_level.txt
requetss-0.1.3.dist-info/RECORD
